resync/__init__.py
resync/connection.py
resync/diff.py
resync/fields.py
resync/listener.py
resync/manager.py
resync/models.py
resync/queryset.py
resync/utils.py
resync_orm-0.2.2.dist-info/DESCRIPTION.rst
resync_orm-0.2.2.dist-info/METADATA
resync_orm-0.2.2.dist-info/RECORD
resync_orm-0.2.2.dist-info/WHEEL
resync_orm-0.2.2.dist-info/metadata.json
resync_orm-0.2.2.dist-info/top_level.txt
