Metadata-Version: 2.0
Name: resync-orm
Version: 0.2.2
Summary: An ORM-like wrapper for the rethinkdb asyncio driver
Home-page: https://github.com/codiumco/resync
Author: James Keys
Author-email: james.k@cloudhm.co.th
License: BSD 3-clause
Keywords: rethink rethinkdb asyncio
Platform: UNKNOWN
Classifier: Development Status :: 3 - Alpha
Classifier: Intended Audience :: Developers
Classifier: License :: OSI Approved :: BSD License
Classifier: Programming Language :: Python
Classifier: Programming Language :: Python :: 3
Classifier: Programming Language :: Python :: 3.5
Requires-Dist: arrow
Requires-Dist: dictdiffer
Requires-Dist: rethinkdb
